{
  "2026-06-11": {
    "win": {
      "Mexico": 0.0,
      "Canada": 0.0,
      "Germany": 0.0,
      "Bosnia and Herzegovina": 0.0,
      "Japan": 0.0,
      "Haiti": 0.0,
      "Morocco": 0.0,
      "Netherlands": 0.0,
      "France": 0.0,
      "Brazil": 0.0,
      "Cote d'Ivoire": 0.0,
      "Iraq": 0.0,
      "Korea Republic": 0.0,
      "Ecuador": 0.0,
      "Croatia": 0.0,
      "Saudi Arabia": 0.0,
      "Australia": 0.0,
      "Senegal": 0.0,
      "Belgium": 0.0,
      "Algeria": 0.0,
      "Colombia": 0.0,
      "England": 0.0,
      "Spain": 0.0,
      "Austria": 0.0,
      "Switzerland": 0.0,
      "Egypt": 0.0,
      "Argentina": 0.0,
      "Uruguay": 0.0,
      "Portugal": 0.0,
      "USA": 0.0,
      "Paraguay": 0.0,
      "IR Iran": 0.0,
      "Czechia": 0.0,
      "Curacao": 0.0,
      "Scotland": 0.0,
      "Sweden": 0.0,
      "Norway": 0.0,
      "Tunisia": 0.0,
      "Uzbekistan": 0.0,
      "Qatar": 0.0,
      "Cabo Verde": 0.0,
      "Ghana": 0.0,
      "Turkey": 0.0,
      "South Africa": 0.0,
      "Jordan": 0.0,
      "New Zealand": 0.0,
      "DR Congo": 0.0,
      "Panama": 0.0
    },
    "final": {
      "Mexico": 4.8500000000000005,
      "Canada": 1.25,
      "Germany": 11.3,
      "Bosnia and Herzegovina": 0.25,
      "Japan": 2.65,
      "Haiti": 0.0,
      "Morocco": 4.75,
      "Netherlands": 8.7,
      "France": 23.3,
      "Brazil": 19.55,
      "Cote d'Ivoire": 0.65,
      "Iraq": 0.1,
      "Korea Republic": 3.5999999999999996,
      "Ecuador": 2.3,
      "Croatia": 2.8000000000000003,
      "Saudi Arabia": 0.3,
      "Australia": 1.6,
      "Senegal": 2.35,
      "Belgium": 8.7,
      "Algeria": 0.5499999999999999,
      "Colombia": 7.35,
      "England": 17.349999999999998,
      "Spain": 16.35,
      "Austria": 2.15,
      "Switzerland": 3.45,
      "Egypt": 0.8500000000000001,
      "Argentina": 17.299999999999997,
      "Uruguay": 4.65,
      "Portugal": 15.55,
      "USA": 5.050000000000001,
      "Paraguay": 0.75,
      "IR Iran": 1.2,
      "Czechia": 0.2,
      "Curacao": 0.2,
      "Scotland": 1.35,
      "Sweden": 0.95,
      "Norway": 1.7500000000000002,
      "Tunisia": 0.4,
      "Uzbekistan": 0.1,
      "Qatar": 0.05,
      "Cabo Verde": 0.15,
      "Ghana": 0.4,
      "Turkey": 2.0500000000000003,
      "South Africa": 0.15,
      "Jordan": 0.1,
      "New Zealand": 0.15,
      "DR Congo": 0.4,
      "Panama": 0.05
    },
    "sf": {
      "Mexico": 11.55,
      "Canada": 3.8,
      "Germany": 19.75,
      "Bosnia and Herzegovina": 1.3,
      "Japan": 7.75,
      "Haiti": 0.05,
      "Morocco": 11.1,
      "Netherlands": 16.45,
      "France": 36.5,
      "Brazil": 31.15,
      "Cote d'Ivoire": 2.1,
      "Iraq": 0.6,
      "Korea Republic": 9.2,
      "Ecuador": 5.1,
      "Croatia": 8.3,
      "Saudi Arabia": 1.5,
      "Australia": 4.95,
      "Senegal": 5.0,
      "Belgium": 18.0,
      "Algeria": 2.0,
      "Colombia": 16.3,
      "England": 29.9,
      "Spain": 28.549999999999997,
      "Austria": 6.15,
      "Switzerland": 9.0,
      "Egypt": 2.0,
      "Argentina": 30.15,
      "Uruguay": 11.15,
      "Portugal": 28.799999999999997,
      "USA": 11.600000000000001,
      "Paraguay": 2.35,
      "IR Iran": 3.5999999999999996,
      "Czechia": 0.95,
      "Curacao": 0.8,
      "Scotland": 2.9000000000000004,
      "Sweden": 3.35,
      "Norway": 4.95,
      "Tunisia": 1.4000000000000001,
      "Uzbekistan": 0.3,
      "Qatar": 0.1,
      "Cabo Verde": 0.44999999999999996,
      "Ghana": 2.3,
      "Turkey": 4.3999999999999995,
      "South Africa": 0.5,
      "Jordan": 0.5499999999999999,
      "New Zealand": 0.25,
      "DR Congo": 0.7000000000000001,
      "Panama": 0.4
    },
    "qf": {
      "Mexico": 26.75,
      "Canada": 11.35,
      "Germany": 35.15,
      "Bosnia and Herzegovina": 5.1499999999999995,
      "Japan": 18.5,
      "Haiti": 1.0,
      "Morocco": 24.85,
      "Netherlands": 33.75,
      "France": 54.6,
      "Brazil": 49.9,
      "Cote d'Ivoire": 7.75,
      "Iraq": 2.7,
      "Korea Republic": 22.7,
      "Ecuador": 11.85,
      "Croatia": 19.05,
      "Saudi Arabia": 4.65,
      "Australia": 15.25,
      "Senegal": 12.75,
      "Belgium": 36.1,
      "Algeria": 6.4,
      "Colombia": 31.6,
      "England": 50.449999999999996,
      "Spain": 43.6,
      "Austria": 14.7,
      "Switzerland": 21.9,
      "Egypt": 7.1,
      "Argentina": 47.15,
      "Uruguay": 22.8,
      "Portugal": 47.699999999999996,
      "USA": 27.450000000000003,
      "Paraguay": 6.45,
      "IR Iran": 10.15,
      "Czechia": 2.85,
      "Curacao": 2.8000000000000003,
      "Scotland": 7.8,
      "Sweden": 8.6,
      "Norway": 13.05,
      "Tunisia": 3.75,
      "Uzbekistan": 1.0999999999999999,
      "Qatar": 1.35,
      "Cabo Verde": 1.5,
      "Ghana": 5.8500000000000005,
      "Turkey": 10.0,
      "South Africa": 2.35,
      "Jordan": 1.7500000000000002,
      "New Zealand": 1.8499999999999999,
      "DR Congo": 2.65,
      "Panama": 1.5
    },
    "r16": {
      "Mexico": 62.74999999999999,
      "Canada": 36.1,
      "Germany": 70.89999999999999,
      "Bosnia and Herzegovina": 19.6,
      "Japan": 34.55,
      "Haiti": 4.35,
      "Morocco": 42.1,
      "Netherlands": 52.05,
      "France": 78.7,
      "Brazil": 67.5,
      "Cote d'Ivoire": 25.650000000000002,
      "Iraq": 9.049999999999999,
      "Korea Republic": 58.15,
      "Ecuador": 34.25,
      "Croatia": 41.4,
      "Saudi Arabia": 10.85,
      "Australia": 37.2,
      "Senegal": 33.900000000000006,
      "Belgium": 66.05,
      "Algeria": 16.35,
      "Colombia": 57.49999999999999,
      "England": 75.3,
      "Spain": 64.60000000000001,
      "Austria": 32.15,
      "Switzerland": 56.99999999999999,
      "Egypt": 23.849999999999998,
      "Argentina": 64.1,
      "Uruguay": 41.199999999999996,
      "Portugal": 70.65,
      "USA": 54.400000000000006,
      "Paraguay": 18.8,
      "IR Iran": 30.65,
      "Czechia": 13.55,
      "Curacao": 11.200000000000001,
      "Scotland": 19.15,
      "Sweden": 18.95,
      "Norway": 33.300000000000004,
      "Tunisia": 9.3,
      "Uzbekistan": 4.45,
      "Qatar": 6.9,
      "Cabo Verde": 4.9,
      "Ghana": 16.35,
      "Turkey": 28.999999999999996,
      "South Africa": 9.85,
      "Jordan": 6.4,
      "New Zealand": 9.049999999999999,
      "DR Congo": 10.549999999999999,
      "Panama": 5.45
    },
    "r32": {
      "Mexico": 98.1,
      "Canada": 82.1,
      "Germany": 96.7,
      "Bosnia and Herzegovina": 62.3,
      "Japan": 81.35,
      "Haiti": 24.05,
      "Morocco": 86.6,
      "Netherlands": 93.10000000000001,
      "France": 98.05,
      "Brazil": 96.89999999999999,
      "Cote d'Ivoire": 62.6,
      "Iraq": 28.7,
      "Korea Republic": 94.65,
      "Ecuador": 71.95,
      "Croatia": 84.7,
      "Saudi Arabia": 47.4,
      "Australia": 73.2,
      "Senegal": 69.6,
      "Belgium": 96.8,
      "Algeria": 53.849999999999994,
      "Colombia": 93.95,
      "England": 97.75,
      "Spain": 97.15,
      "Austria": 82.8,
      "Switzerland": 93.95,
      "Egypt": 65.64999999999999,
      "Argentina": 97.35000000000001,
      "Uruguay": 89.05,
      "Portugal": 96.95,
      "USA": 87.55,
      "Paraguay": 48.1,
      "IR Iran": 72.7,
      "Czechia": 43.4,
      "Curacao": 36.7,
      "Scotland": 59.699999999999996,
      "Sweden": 60.6,
      "Norway": 67.35,
      "Tunisia": 35.55,
      "Uzbekistan": 25.8,
      "Qatar": 33.050000000000004,
      "Cabo Verde": 29.15,
      "Ghana": 51.849999999999994,
      "Turkey": 63.449999999999996,
      "South Africa": 31.6,
      "Jordan": 32.4,
      "New Zealand": 32.05,
      "DR Congo": 44.05,
      "Panama": 27.650000000000002
    },
    "_match_count": 2
  },
  "2026-06-12": {
    "win": {
      "Czechia": 0.0,
      "Bosnia and Herzegovina": 0.0,
      "Germany": 0.0,
      "Mexico": 0.0,
      "Japan": 0.0,
      "Morocco": 0.0,
      "Brazil": 0.0,
      "Netherlands": 0.0,
      "Senegal": 0.0,
      "Sweden": 0.0,
      "Ecuador": 0.0,
      "Iraq": 0.0,
      "Korea Republic": 0.0,
      "Cabo Verde": 0.0,
      "England": 0.0,
      "DR Congo": 0.0,
      "USA": 0.0,
      "Canada": 0.0,
      "Belgium": 0.0,
      "Norway": 0.0,
      "Portugal": 0.0,
      "Ghana": 0.0,
      "Uruguay": 0.0,
      "Algeria": 0.0,
      "Qatar": 0.0,
      "Jordan": 0.0,
      "Argentina": 0.0,
      "Spain": 0.0,
      "Colombia": 0.0,
      "Croatia": 0.0,
      "Australia": 0.0,
      "Egypt": 0.0,
      "Scotland": 0.0,
      "France": 0.0,
      "Cote d'Ivoire": 0.0,
      "Turkey": 0.0,
      "Saudi Arabia": 0.0,
      "Austria": 0.0,
      "Switzerland": 0.0,
      "South Africa": 0.0,
      "Paraguay": 0.0,
      "Curacao": 0.0,
      "Tunisia": 0.0,
      "IR Iran": 0.0,
      "Uzbekistan": 0.0,
      "New Zealand": 0.0,
      "Panama": 0.0,
      "Haiti": 0.0
    },
    "final": {
      "Czechia": 0.35000000000000003,
      "Bosnia and Herzegovina": 0.15,
      "Germany": 12.0,
      "Mexico": 5.1499999999999995,
      "Japan": 3.05,
      "Morocco": 5.3,
      "Brazil": 20.4,
      "Netherlands": 9.4,
      "Senegal": 2.3,
      "Sweden": 1.0,
      "Ecuador": 1.7000000000000002,
      "Iraq": 0.1,
      "Korea Republic": 2.9499999999999997,
      "Cabo Verde": 0.2,
      "England": 18.35,
      "DR Congo": 0.1,
      "USA": 7.6,
      "Canada": 0.8,
      "Belgium": 9.2,
      "Norway": 1.5,
      "Portugal": 14.75,
      "Ghana": 0.75,
      "Uruguay": 3.75,
      "Algeria": 0.44999999999999996,
      "Qatar": 0.0,
      "Jordan": 0.1,
      "Argentina": 16.650000000000002,
      "Spain": 13.350000000000001,
      "Colombia": 6.35,
      "Croatia": 3.85,
      "Australia": 2.5,
      "Egypt": 0.44999999999999996,
      "Scotland": 0.75,
      "France": 22.8,
      "Cote d'Ivoire": 0.7000000000000001,
      "Turkey": 1.6,
      "Saudi Arabia": 0.35000000000000003,
      "Austria": 2.8000000000000003,
      "Switzerland": 3.75,
      "South Africa": 0.15,
      "Paraguay": 0.15,
      "Curacao": 0.25,
      "Tunisia": 0.44999999999999996,
      "IR Iran": 1.25,
      "Uzbekistan": 0.15,
      "New Zealand": 0.05,
      "Panama": 0.15,
      "Haiti": 0.1
    },
    "sf": {
      "Czechia": 0.95,
      "Bosnia and Herzegovina": 1.2,
      "Germany": 20.849999999999998,
      "Mexico": 11.85,
      "Japan": 6.950000000000001,
      "Morocco": 11.95,
      "Brazil": 31.65,
      "Netherlands": 17.05,
      "Senegal": 4.95,
      "Sweden": 3.05,
      "Ecuador": 4.8500000000000005,
      "Iraq": 0.25,
      "Korea Republic": 7.1,
      "Cabo Verde": 0.8500000000000001,
      "England": 30.8,
      "DR Congo": 0.95,
      "USA": 16.45,
      "Canada": 3.3000000000000003,
      "Belgium": 20.4,
      "Norway": 4.2,
      "Portugal": 27.250000000000004,
      "Ghana": 1.6,
      "Uruguay": 10.2,
      "Algeria": 1.5,
      "Qatar": 0.1,
      "Jordan": 0.35000000000000003,
      "Argentina": 30.65,
      "Spain": 25.4,
      "Colombia": 15.45,
      "Croatia": 8.450000000000001,
      "Australia": 6.4,
      "Egypt": 1.7000000000000002,
      "Scotland": 2.7,
      "France": 35.75,
      "Cote d'Ivoire": 2.4,
      "Turkey": 4.3999999999999995,
      "Saudi Arabia": 0.95,
      "Austria": 7.199999999999999,
      "Switzerland": 9.65,
      "South Africa": 0.7000000000000001,
      "Paraguay": 0.75,
      "Curacao": 0.95,
      "Tunisia": 1.0,
      "IR Iran": 3.3000000000000003,
      "Uzbekistan": 0.35000000000000003,
      "New Zealand": 0.6,
      "Panama": 0.44999999999999996,
      "Haiti": 0.2
    },
    "qf": {
      "Czechia": 3.1,
      "Bosnia and Herzegovina": 5.4,
      "Germany": 37.3,
      "Mexico": 29.45,
      "Japan": 16.75,
      "Morocco": 25.650000000000002,
      "Brazil": 50.9,
      "Netherlands": 34.4,
      "Senegal": 13.15,
      "Sweden": 9.35,
      "Ecuador": 10.7,
      "Iraq": 1.2,
      "Korea Republic": 20.599999999999998,
      "Cabo Verde": 2.5,
      "England": 51.800000000000004,
      "DR Congo": 2.85,
      "USA": 33.900000000000006,
      "Canada": 9.950000000000001,
      "Belgium": 39.550000000000004,
      "Norway": 9.9,
      "Portugal": 49.3,
      "Ghana": 5.55,
      "Uruguay": 22.1,
      "Algeria": 5.25,
      "Qatar": 0.95,
      "Jordan": 1.95,
      "Argentina": 48.25,
      "Spain": 41.0,
      "Colombia": 31.75,
      "Croatia": 18.55,
      "Australia": 14.000000000000002,
      "Egypt": 5.949999999999999,
      "Scotland": 8.1,
      "France": 53.300000000000004,
      "Cote d'Ivoire": 7.1,
      "Turkey": 11.200000000000001,
      "Saudi Arabia": 3.95,
      "Austria": 14.6,
      "Switzerland": 22.8,
      "South Africa": 2.9499999999999997,
      "Paraguay": 2.3,
      "Curacao": 2.65,
      "Tunisia": 3.05,
      "IR Iran": 9.2,
      "Uzbekistan": 1.3,
      "New Zealand": 2.1999999999999997,
      "Panama": 0.8500000000000001,
      "Haiti": 1.4500000000000002
    },
    "r16": {
      "Czechia": 14.299999999999999,
      "Bosnia and Herzegovina": 23.400000000000002,
      "Germany": 71.85000000000001,
      "Mexico": 64.3,
      "Japan": 33.050000000000004,
      "Morocco": 42.35,
      "Brazil": 68.95,
      "Netherlands": 51.6,
      "Senegal": 34.449999999999996,
      "Sweden": 20.549999999999997,
      "Ecuador": 33.25,
      "Iraq": 7.7,
      "Korea Republic": 56.2,
      "Cabo Verde": 6.2,
      "England": 76.7,
      "DR Congo": 10.299999999999999,
      "USA": 65.5,
      "Canada": 32.2,
      "Belgium": 69.19999999999999,
      "Norway": 29.099999999999998,
      "Portugal": 71.3,
      "Ghana": 16.1,
      "Uruguay": 42.05,
      "Algeria": 16.25,
      "Qatar": 6.35,
      "Jordan": 6.7,
      "Argentina": 64.75,
      "Spain": 62.2,
      "Colombia": 57.099999999999994,
      "Croatia": 41.4,
      "Australia": 37.95,
      "Egypt": 23.9,
      "Scotland": 17.5,
      "France": 78.7,
      "Cote d'Ivoire": 25.1,
      "Turkey": 28.7,
      "Saudi Arabia": 11.75,
      "Austria": 31.2,
      "Switzerland": 58.35,
      "South Africa": 10.75,
      "Paraguay": 8.95,
      "Curacao": 11.3,
      "Tunisia": 8.450000000000001,
      "IR Iran": 29.599999999999998,
      "Uzbekistan": 4.35,
      "New Zealand": 8.4,
      "Panama": 4.9,
      "Haiti": 4.8
    },
    "r32": {
      "Czechia": 43.35,
      "Bosnia and Herzegovina": 67.65,
      "Germany": 95.45,
      "Mexico": 98.2,
      "Japan": 81.39999999999999,
      "Morocco": 89.1,
      "Brazil": 97.35000000000001,
      "Netherlands": 92.80000000000001,
      "Senegal": 72.3,
      "Sweden": 61.199999999999996,
      "Ecuador": 72.25,
      "Iraq": 28.65,
      "Korea Republic": 94.0,
      "Cabo Verde": 28.95,
      "England": 97.85000000000001,
      "DR Congo": 43.55,
      "USA": 98.7,
      "Canada": 78.10000000000001,
      "Belgium": 97.1,
      "Norway": 66.60000000000001,
      "Portugal": 97.1,
      "Ghana": 55.1,
      "Uruguay": 90.3,
      "Algeria": 54.25,
      "Qatar": 30.3,
      "Jordan": 30.8,
      "Argentina": 97.5,
      "Spain": 96.95,
      "Colombia": 93.55,
      "Croatia": 85.85000000000001,
      "Australia": 74.5,
      "Egypt": 65.14999999999999,
      "Scotland": 59.150000000000006,
      "France": 97.85000000000001,
      "Cote d'Ivoire": 61.550000000000004,
      "Turkey": 63.5,
      "Saudi Arabia": 46.550000000000004,
      "Austria": 83.55,
      "Switzerland": 93.55,
      "South Africa": 31.5,
      "Paraguay": 28.9,
      "Curacao": 38.9,
      "Tunisia": 35.55,
      "IR Iran": 72.3,
      "Uzbekistan": 27.200000000000003,
      "New Zealand": 34.599999999999994,
      "Panama": 26.450000000000003,
      "Haiti": 23.0
    },
    "_match_count": 4
  },
  "2026-06-13": {
    "win": {
      "Czechia": 0.0,
      "Bosnia and Herzegovina": 0.0,
      "Germany": 0.0,
      "Mexico": 0.0,
      "Netherlands": 0.0,
      "Brazil": 0.0,
      "Morocco": 0.0,
      "Sweden": 0.0,
      "France": 0.0,
      "Scotland": 0.0,
      "Ecuador": 0.0,
      "Senegal": 0.0,
      "Korea Republic": 0.0,
      "Tunisia": 0.0,
      "England": 0.0,
      "Saudi Arabia": 0.0,
      "USA": 0.0,
      "Switzerland": 0.0,
      "Belgium": 0.0,
      "Algeria": 0.0,
      "Portugal": 0.0,
      "Croatia": 0.0,
      "Uruguay": 0.0,
      "Austria": 0.0,
      "Qatar": 0.0,
      "Egypt": 0.0,
      "Argentina": 0.0,
      "Spain": 0.0,
      "Colombia": 0.0,
      "Australia": 0.0,
      "Turkey": 0.0,
      "IR Iran": 0.0,
      "South Africa": 0.0,
      "Japan": 0.0,
      "Norway": 0.0,
      "Iraq": 0.0,
      "Cabo Verde": 0.0,
      "DR Congo": 0.0,
      "Canada": 0.0,
      "Ghana": 0.0,
      "Jordan": 0.0,
      "New Zealand": 0.0,
      "Cote d'Ivoire": 0.0,
      "Panama": 0.0,
      "Uzbekistan": 0.0,
      "Paraguay": 0.0,
      "Curacao": 0.0,
      "Haiti": 0.0
    },
    "final": {
      "Czechia": 0.5,
      "Bosnia and Herzegovina": 0.7000000000000001,
      "Germany": 11.5,
      "Mexico": 4.6,
      "Netherlands": 8.95,
      "Brazil": 15.299999999999999,
      "Morocco": 6.4,
      "Sweden": 1.15,
      "France": 23.1,
      "Scotland": 1.95,
      "Ecuador": 1.5,
      "Senegal": 2.55,
      "Korea Republic": 2.9000000000000004,
      "Tunisia": 0.1,
      "England": 20.349999999999998,
      "Saudi Arabia": 0.5499999999999999,
      "USA": 6.05,
      "Switzerland": 3.1,
      "Belgium": 8.649999999999999,
      "Algeria": 0.4,
      "Portugal": 14.899999999999999,
      "Croatia": 2.4,
      "Uruguay": 4.25,
      "Austria": 2.7,
      "Qatar": 0.1,
      "Egypt": 0.4,
      "Argentina": 17.9,
      "Spain": 15.4,
      "Colombia": 7.249999999999999,
      "Australia": 2.1,
      "Turkey": 1.6,
      "IR Iran": 0.95,
      "South Africa": 0.1,
      "Japan": 3.55,
      "Norway": 1.95,
      "Iraq": 0.1,
      "Cabo Verde": 0.1,
      "DR Congo": 0.05,
      "Canada": 1.0999999999999999,
      "Ghana": 0.75,
      "Jordan": 0.1,
      "New Zealand": 0.05,
      "Cote d'Ivoire": 1.05,
      "Panama": 0.05,
      "Uzbekistan": 0.0,
      "Paraguay": 0.3,
      "Curacao": 0.44999999999999996,
      "Haiti": 0.05
    },
    "sf": {
      "Czechia": 1.0,
      "Bosnia and Herzegovina": 1.5,
      "Germany": 20.45,
      "Mexico": 10.299999999999999,
      "Netherlands": 16.8,
      "Brazil": 26.0,
      "Morocco": 13.4,
      "Sweden": 3.55,
      "France": 35.0,
      "Scotland": 4.55,
      "Ecuador": 4.8,
      "Senegal": 6.2,
      "Korea Republic": 6.65,
      "Tunisia": 0.65,
      "England": 33.550000000000004,
      "Saudi Arabia": 1.05,
      "USA": 15.25,
      "Switzerland": 7.55,
      "Belgium": 19.3,
      "Algeria": 1.7999999999999998,
      "Portugal": 28.4,
      "Croatia": 7.55,
      "Uruguay": 10.45,
      "Austria": 7.249999999999999,
      "Qatar": 0.5499999999999999,
      "Egypt": 1.7000000000000002,
      "Argentina": 31.65,
      "Spain": 27.200000000000003,
      "Colombia": 16.1,
      "Australia": 5.55,
      "Turkey": 4.65,
      "IR Iran": 2.8000000000000003,
      "South Africa": 0.7000000000000001,
      "Japan": 7.3,
      "Norway": 4.7,
      "Iraq": 1.15,
      "Cabo Verde": 0.4,
      "DR Congo": 0.65,
      "Canada": 3.4000000000000004,
      "Ghana": 1.9,
      "Jordan": 0.44999999999999996,
      "New Zealand": 0.5,
      "Cote d'Ivoire": 2.85,
      "Panama": 0.3,
      "Uzbekistan": 0.3,
      "Paraguay": 0.95,
      "Curacao": 1.0,
      "Haiti": 0.25
    },
    "qf": {
      "Czechia": 3.4000000000000004,
      "Bosnia and Herzegovina": 4.8,
      "Germany": 34.449999999999996,
      "Mexico": 26.0,
      "Netherlands": 33.900000000000006,
      "Brazil": 44.65,
      "Morocco": 29.299999999999997,
      "Sweden": 9.2,
      "France": 52.2,
      "Scotland": 12.2,
      "Ecuador": 11.700000000000001,
      "Senegal": 15.049999999999999,
      "Korea Republic": 18.85,
      "Tunisia": 2.8000000000000003,
      "England": 53.5,
      "Saudi Arabia": 4.3,
      "USA": 35.099999999999994,
      "Switzerland": 19.05,
      "Belgium": 37.9,
      "Algeria": 5.35,
      "Portugal": 50.0,
      "Croatia": 17.599999999999998,
      "Uruguay": 21.55,
      "Austria": 16.25,
      "Qatar": 2.0500000000000003,
      "Egypt": 6.5,
      "Argentina": 47.5,
      "Spain": 42.55,
      "Colombia": 31.8,
      "Australia": 15.45,
      "Turkey": 10.85,
      "IR Iran": 10.05,
      "South Africa": 3.35,
      "Japan": 17.5,
      "Norway": 12.1,
      "Iraq": 2.35,
      "Cabo Verde": 1.6500000000000001,
      "DR Congo": 3.0,
      "Canada": 10.05,
      "Ghana": 5.050000000000001,
      "Jordan": 1.7999999999999998,
      "New Zealand": 1.9,
      "Cote d'Ivoire": 7.55,
      "Panama": 1.0,
      "Uzbekistan": 1.3,
      "Paraguay": 2.65,
      "Curacao": 2.55,
      "Haiti": 0.35000000000000003
    },
    "r16": {
      "Czechia": 14.649999999999999,
      "Bosnia and Herzegovina": 22.45,
      "Germany": 70.39999999999999,
      "Mexico": 62.7,
      "Netherlands": 51.449999999999996,
      "Brazil": 63.5,
      "Morocco": 48.15,
      "Sweden": 21.349999999999998,
      "France": 77.14999999999999,
      "Scotland": 26.700000000000003,
      "Ecuador": 33.7,
      "Senegal": 35.75,
      "Korea Republic": 54.800000000000004,
      "Tunisia": 8.9,
      "England": 75.85,
      "Saudi Arabia": 11.3,
      "USA": 66.55,
      "Switzerland": 47.3,
      "Belgium": 68.2,
      "Algeria": 14.649999999999999,
      "Portugal": 71.7,
      "Croatia": 39.15,
      "Uruguay": 39.75,
      "Austria": 32.1,
      "Qatar": 11.450000000000001,
      "Egypt": 24.15,
      "Argentina": 66.25,
      "Spain": 63.24999999999999,
      "Colombia": 57.65,
      "Australia": 37.95,
      "Turkey": 29.299999999999997,
      "IR Iran": 31.25,
      "South Africa": 11.450000000000001,
      "Japan": 33.050000000000004,
      "Norway": 30.75,
      "Iraq": 8.649999999999999,
      "Cabo Verde": 5.2,
      "DR Congo": 10.7,
      "Canada": 31.900000000000002,
      "Ghana": 14.85,
      "Jordan": 7.199999999999999,
      "New Zealand": 10.100000000000001,
      "Cote d'Ivoire": 25.55,
      "Panama": 5.1,
      "Uzbekistan": 4.35,
      "Paraguay": 8.799999999999999,
      "Curacao": 11.35,
      "Haiti": 1.55
    },
    "r32": {
      "Czechia": 41.65,
      "Bosnia and Herzegovina": 62.949999999999996,
      "Germany": 96.89999999999999,
      "Mexico": 98.5,
      "Netherlands": 92.95,
      "Brazil": 97.5,
      "Morocco": 93.15,
      "Sweden": 62.35000000000001,
      "France": 97.7,
      "Scotland": 75.55,
      "Ecuador": 71.25,
      "Senegal": 71.89999999999999,
      "Korea Republic": 93.55,
      "Tunisia": 36.05,
      "England": 98.05,
      "Saudi Arabia": 46.5,
      "USA": 98.6,
      "Switzerland": 84.2,
      "Belgium": 96.85000000000001,
      "Algeria": 52.2,
      "Portugal": 97.3,
      "Croatia": 84.1,
      "Uruguay": 89.05,
      "Austria": 82.8,
      "Qatar": 47.65,
      "Egypt": 62.55,
      "Argentina": 97.6,
      "Spain": 97.05,
      "Colombia": 94.35,
      "Australia": 75.4,
      "Turkey": 67.05,
      "IR Iran": 73.15,
      "South Africa": 33.2,
      "Japan": 80.95,
      "Norway": 69.55,
      "Iraq": 28.050000000000004,
      "Cabo Verde": 29.299999999999997,
      "DR Congo": 43.65,
      "Canada": 75.1,
      "Ghana": 53.949999999999996,
      "Jordan": 31.25,
      "New Zealand": 33.6,
      "Cote d'Ivoire": 61.0,
      "Panama": 28.65,
      "Uzbekistan": 23.65,
      "Paraguay": 26.700000000000003,
      "Curacao": 36.9,
      "Haiti": 8.1
    },
    "_match_count": 7
  },
  "2026-06-14": {
    "win": {
      "Korea Republic": 0.0,
      "Qatar": 0.0,
      "Germany": 0.0,
      "Czechia": 0.0,
      "Sweden": 0.0,
      "Brazil": 0.0,
      "Morocco": 0.0,
      "Netherlands": 0.0,
      "France": 0.0,
      "Paraguay": 0.0,
      "Cote d'Ivoire": 0.0,
      "Senegal": 0.0,
      "Mexico": 0.0,
      "Japan": 0.0,
      "Croatia": 0.0,
      "Portugal": 0.0,
      "USA": 0.0,
      "Canada": 0.0,
      "Belgium": 0.0,
      "Spain": 0.0,
      "DR Congo": 0.0,
      "England": 0.0,
      "Saudi Arabia": 0.0,
      "Algeria": 0.0,
      "Switzerland": 0.0,
      "Iraq": 0.0,
      "Argentina": 0.0,
      "Uruguay": 0.0,
      "Colombia": 0.0,
      "Austria": 0.0,
      "Australia": 0.0,
      "New Zealand": 0.0,
      "Bosnia and Herzegovina": 0.0,
      "Norway": 0.0,
      "Ghana": 0.0,
      "Cabo Verde": 0.0,
      "IR Iran": 0.0,
      "Scotland": 0.0,
      "Ecuador": 0.0,
      "Uzbekistan": 0.0,
      "South Africa": 0.0,
      "Egypt": 0.0,
      "Turkey": 0.0,
      "Haiti": 0.0,
      "Tunisia": 0.0,
      "Jordan": 0.0,
      "Curacao": 0.0,
      "Panama": 0.0
    },
    "final": {
      "Korea Republic": 2.9000000000000004,
      "Qatar": 0.25,
      "Germany": 13.750000000000002,
      "Czechia": 0.5,
      "Sweden": 2.1999999999999997,
      "Brazil": 16.25,
      "Morocco": 6.5,
      "Netherlands": 8.3,
      "France": 21.5,
      "Paraguay": 0.25,
      "Cote d'Ivoire": 2.3,
      "Senegal": 2.55,
      "Mexico": 5.050000000000001,
      "Japan": 3.25,
      "Croatia": 3.05,
      "Portugal": 15.65,
      "USA": 6.0,
      "Canada": 1.0,
      "Belgium": 8.450000000000001,
      "Spain": 14.649999999999999,
      "DR Congo": 0.44999999999999996,
      "England": 19.400000000000002,
      "Saudi Arabia": 0.35000000000000003,
      "Algeria": 0.6,
      "Switzerland": 2.45,
      "Iraq": 0.15,
      "Argentina": 16.5,
      "Uruguay": 4.25,
      "Colombia": 7.6499999999999995,
      "Austria": 2.4,
      "Australia": 3.85,
      "New Zealand": 0.1,
      "Bosnia and Herzegovina": 0.2,
      "Norway": 1.6,
      "Ghana": 0.5499999999999999,
      "Cabo Verde": 0.05,
      "IR Iran": 1.0999999999999999,
      "Scotland": 1.55,
      "Ecuador": 0.75,
      "Uzbekistan": 0.0,
      "South Africa": 0.3,
      "Egypt": 0.5,
      "Turkey": 0.44999999999999996,
      "Haiti": 0.05,
      "Tunisia": 0.0,
      "Jordan": 0.15,
      "Curacao": 0.1,
      "Panama": 0.15
    },
    "sf": {
      "Korea Republic": 7.049999999999999,
      "Qatar": 0.6,
      "Germany": 23.599999999999998,
      "Czechia": 1.0999999999999999,
      "Sweden": 5.800000000000001,
      "Brazil": 26.900000000000002,
      "Morocco": 13.4,
      "Netherlands": 16.5,
      "France": 33.95,
      "Paraguay": 0.95,
      "Cote d'Ivoire": 5.4,
      "Senegal": 5.35,
      "Mexico": 11.75,
      "Japan": 7.3,
      "Croatia": 8.6,
      "Portugal": 29.95,
      "USA": 14.299999999999999,
      "Canada": 3.05,
      "Belgium": 18.85,
      "Spain": 26.200000000000003,
      "DR Congo": 1.0,
      "England": 32.15,
      "Saudi Arabia": 1.15,
      "Algeria": 1.6500000000000001,
      "Switzerland": 6.6000000000000005,
      "Iraq": 0.35000000000000003,
      "Argentina": 28.65,
      "Uruguay": 10.549999999999999,
      "Colombia": 18.5,
      "Austria": 5.949999999999999,
      "Australia": 9.5,
      "New Zealand": 0.4,
      "Bosnia and Herzegovina": 1.0999999999999999,
      "Norway": 4.3,
      "Ghana": 1.95,
      "Cabo Verde": 0.5499999999999999,
      "IR Iran": 3.45,
      "Scotland": 3.45,
      "Ecuador": 2.55,
      "Uzbekistan": 0.1,
      "South Africa": 0.7000000000000001,
      "Egypt": 1.7500000000000002,
      "Turkey": 1.4000000000000001,
      "Haiti": 0.05,
      "Tunisia": 0.25,
      "Jordan": 0.65,
      "Curacao": 0.2,
      "Panama": 0.5
    },
    "qf": {
      "Korea Republic": 21.099999999999998,
      "Qatar": 2.1999999999999997,
      "Germany": 38.15,
      "Czechia": 3.25,
      "Sweden": 16.950000000000003,
      "Brazil": 44.5,
      "Morocco": 28.749999999999996,
      "Netherlands": 32.35,
      "France": 50.2,
      "Paraguay": 2.45,
      "Cote d'Ivoire": 14.149999999999999,
      "Senegal": 13.65,
      "Mexico": 27.05,
      "Japan": 19.25,
      "Croatia": 18.6,
      "Portugal": 49.25,
      "USA": 33.650000000000006,
      "Canada": 9.5,
      "Belgium": 38.3,
      "Spain": 42.55,
      "DR Congo": 3.5000000000000004,
      "England": 52.5,
      "Saudi Arabia": 4.0,
      "Algeria": 5.2,
      "Switzerland": 17.05,
      "Iraq": 2.1,
      "Argentina": 45.25,
      "Uruguay": 22.1,
      "Colombia": 34.75,
      "Austria": 14.2,
      "Australia": 22.75,
      "New Zealand": 1.4000000000000001,
      "Bosnia and Herzegovina": 5.25,
      "Norway": 11.5,
      "Ghana": 5.4,
      "Cabo Verde": 1.6500000000000001,
      "IR Iran": 9.1,
      "Scotland": 10.6,
      "Ecuador": 6.4,
      "Uzbekistan": 1.05,
      "South Africa": 1.95,
      "Egypt": 6.3,
      "Turkey": 4.9,
      "Haiti": 0.3,
      "Tunisia": 0.44999999999999996,
      "Jordan": 2.25,
      "Curacao": 0.7000000000000001,
      "Panama": 1.55
    },
    "r16": {
      "Korea Republic": 55.1,
      "Qatar": 12.85,
      "Germany": 75.25,
      "Czechia": 12.4,
      "Sweden": 35.05,
      "Brazil": 62.7,
      "Morocco": 48.25,
      "Netherlands": 50.449999999999996,
      "France": 76.55,
      "Paraguay": 7.95,
      "Cote d'Ivoire": 45.0,
      "Senegal": 35.449999999999996,
      "Mexico": 62.4,
      "Japan": 36.25,
      "Croatia": 40.699999999999996,
      "Portugal": 71.1,
      "USA": 65.2,
      "Canada": 31.45,
      "Belgium": 67.0,
      "Spain": 65.14999999999999,
      "DR Congo": 10.8,
      "England": 75.75,
      "Saudi Arabia": 10.8,
      "Algeria": 14.799999999999999,
      "Switzerland": 47.65,
      "Iraq": 8.649999999999999,
      "Argentina": 63.0,
      "Uruguay": 40.35,
      "Colombia": 58.599999999999994,
      "Austria": 33.050000000000004,
      "Australia": 56.00000000000001,
      "New Zealand": 9.6,
      "Bosnia and Herzegovina": 21.349999999999998,
      "Norway": 30.5,
      "Ghana": 15.5,
      "Cabo Verde": 5.4,
      "IR Iran": 30.2,
      "Scotland": 24.65,
      "Ecuador": 17.7,
      "Uzbekistan": 5.0,
      "South Africa": 8.649999999999999,
      "Egypt": 24.6,
      "Turkey": 11.450000000000001,
      "Haiti": 1.4500000000000002,
      "Tunisia": 1.7500000000000002,
      "Jordan": 7.3999999999999995,
      "Curacao": 4.5,
      "Panama": 4.6
    },
    "r32": {
      "Korea Republic": 95.3,
      "Qatar": 48.199999999999996,
      "Germany": 99.55000000000001,
      "Czechia": 41.25,
      "Sweden": 96.89999999999999,
      "Brazil": 96.55,
      "Morocco": 93.60000000000001,
      "Netherlands": 92.75,
      "France": 98.4,
      "Paraguay": 26.85,
      "Cote d'Ivoire": 92.45,
      "Senegal": 72.35000000000001,
      "Mexico": 97.85000000000001,
      "Japan": 86.3,
      "Croatia": 85.7,
      "Portugal": 97.3,
      "USA": 98.95,
      "Canada": 74.1,
      "Belgium": 96.6,
      "Spain": 97.65,
      "DR Congo": 44.0,
      "England": 98.15,
      "Saudi Arabia": 46.5,
      "Algeria": 52.1,
      "Switzerland": 84.6,
      "Iraq": 28.849999999999998,
      "Argentina": 97.89999999999999,
      "Uruguay": 89.14999999999999,
      "Colombia": 94.5,
      "Austria": 83.39999999999999,
      "Australia": 97.05,
      "New Zealand": 34.0,
      "Bosnia and Herzegovina": 64.5,
      "Norway": 67.85,
      "Ghana": 52.900000000000006,
      "Cabo Verde": 28.050000000000004,
      "IR Iran": 70.8,
      "Scotland": 73.9,
      "Ecuador": 52.0,
      "Uzbekistan": 25.35,
      "South Africa": 30.5,
      "Egypt": 64.25,
      "Turkey": 38.25,
      "Haiti": 9.9,
      "Tunisia": 7.8,
      "Jordan": 32.25,
      "Curacao": 16.85,
      "Panama": 26.05
    },
    "_match_count": 12
  },
  "2026-06-15": {
    "win": {
      "Korea Republic": 0.0,
      "Qatar": 0.0,
      "Germany": 0.0,
      "South Africa": 0.0,
      "Sweden": 0.0,
      "Morocco": 0.0,
      "Brazil": 0.0,
      "Japan": 0.0,
      "Norway": 0.0,
      "Australia": 0.0,
      "Ecuador": 0.0,
      "France": 0.0,
      "Mexico": 0.0,
      "Cote d'Ivoire": 0.0,
      "England": 0.0,
      "Senegal": 0.0,
      "USA": 0.0,
      "Netherlands": 0.0,
      "IR Iran": 0.0,
      "Jordan": 0.0,
      "Colombia": 0.0,
      "Croatia": 0.0,
      "Spain": 0.0,
      "Argentina": 0.0,
      "Switzerland": 0.0,
      "Belgium": 0.0,
      "Austria": 0.0,
      "Uruguay": 0.0,
      "Portugal": 0.0,
      "Ghana": 0.0,
      "Paraguay": 0.0,
      "Egypt": 0.0,
      "Czechia": 0.0,
      "Bosnia and Herzegovina": 0.0,
      "Cabo Verde": 0.0,
      "DR Congo": 0.0,
      "Algeria": 0.0,
      "Canada": 0.0,
      "Saudi Arabia": 0.0,
      "Scotland": 0.0,
      "Iraq": 0.0,
      "New Zealand": 0.0,
      "Panama": 0.0,
      "Turkey": 0.0,
      "Uzbekistan": 0.0,
      "Haiti": 0.0,
      "Curacao": 0.0,
      "Tunisia": 0.0
    },
    "final": {
      "Korea Republic": 2.8000000000000003,
      "Qatar": 0.15,
      "Germany": 12.7,
      "South Africa": 0.2,
      "Sweden": 2.6,
      "Morocco": 6.3,
      "Brazil": 16.35,
      "Japan": 3.85,
      "Norway": 1.6500000000000001,
      "Australia": 3.1,
      "Ecuador": 0.8,
      "France": 21.4,
      "Mexico": 5.2,
      "Cote d'Ivoire": 2.3,
      "England": 18.65,
      "Senegal": 2.1999999999999997,
      "USA": 6.7,
      "Netherlands": 9.45,
      "IR Iran": 0.65,
      "Jordan": 0.1,
      "Colombia": 7.95,
      "Croatia": 2.9000000000000004,
      "Spain": 12.3,
      "Argentina": 17.599999999999998,
      "Switzerland": 2.7,
      "Belgium": 8.55,
      "Austria": 2.9499999999999997,
      "Uruguay": 2.9000000000000004,
      "Portugal": 16.85,
      "Ghana": 0.44999999999999996,
      "Paraguay": 0.3,
      "Egypt": 1.0,
      "Czechia": 0.35000000000000003,
      "Bosnia and Herzegovina": 0.4,
      "Cabo Verde": 0.4,
      "DR Congo": 0.15,
      "Algeria": 0.65,
      "Canada": 0.8500000000000001,
      "Saudi Arabia": 0.65,
      "Scotland": 2.15,
      "Iraq": 0.05,
      "New Zealand": 0.0,
      "Panama": 0.05,
      "Turkey": 0.44999999999999996,
      "Uzbekistan": 0.1,
      "Haiti": 0.05,
      "Curacao": 0.0,
      "Tunisia": 0.1
    },
    "sf": {
      "Korea Republic": 7.5,
      "Qatar": 0.6,
      "Germany": 22.400000000000002,
      "South Africa": 0.65,
      "Sweden": 5.8500000000000005,
      "Morocco": 13.05,
      "Brazil": 27.6,
      "Japan": 8.200000000000001,
      "Norway": 4.2,
      "Australia": 8.85,
      "Ecuador": 2.0500000000000003,
      "France": 33.800000000000004,
      "Mexico": 11.25,
      "Cote d'Ivoire": 5.7,
      "England": 32.0,
      "Senegal": 5.8500000000000005,
      "USA": 15.75,
      "Netherlands": 16.35,
      "IR Iran": 1.8499999999999999,
      "Jordan": 0.5499999999999999,
      "Colombia": 17.65,
      "Croatia": 7.55,
      "Spain": 22.400000000000002,
      "Argentina": 32.35,
      "Switzerland": 6.7,
      "Belgium": 17.65,
      "Austria": 8.1,
      "Uruguay": 8.75,
      "Portugal": 30.7,
      "Ghana": 1.25,
      "Paraguay": 1.0999999999999999,
      "Egypt": 3.2,
      "Czechia": 0.75,
      "Bosnia and Herzegovina": 1.35,
      "Cabo Verde": 1.35,
      "DR Congo": 0.6,
      "Algeria": 2.25,
      "Canada": 2.55,
      "Saudi Arabia": 1.95,
      "Scotland": 4.35,
      "Iraq": 0.3,
      "New Zealand": 0.6,
      "Panama": 0.25,
      "Turkey": 1.5,
      "Uzbekistan": 0.25,
      "Haiti": 0.1,
      "Curacao": 0.25,
      "Tunisia": 0.15
    },
    "qf": {
      "Korea Republic": 21.05,
      "Qatar": 2.4,
      "Germany": 38.800000000000004,
      "South Africa": 3.2,
      "Sweden": 16.85,
      "Morocco": 29.2,
      "Brazil": 46.300000000000004,
      "Japan": 19.25,
      "Norway": 11.35,
      "Australia": 21.9,
      "Ecuador": 5.800000000000001,
      "France": 49.3,
      "Mexico": 27.1,
      "Cote d'Ivoire": 15.45,
      "England": 50.849999999999994,
      "Senegal": 13.900000000000002,
      "USA": 33.15,
      "Netherlands": 31.3,
      "IR Iran": 6.1,
      "Jordan": 2.0,
      "Colombia": 33.5,
      "Croatia": 18.55,
      "Spain": 36.0,
      "Argentina": 49.3,
      "Switzerland": 17.549999999999997,
      "Belgium": 35.35,
      "Austria": 17.349999999999998,
      "Uruguay": 19.05,
      "Portugal": 51.2,
      "Ghana": 5.55,
      "Paraguay": 2.8000000000000003,
      "Egypt": 9.4,
      "Czechia": 2.8000000000000003,
      "Bosnia and Herzegovina": 5.5,
      "Cabo Verde": 3.2,
      "DR Congo": 2.75,
      "Algeria": 5.8999999999999995,
      "Canada": 8.75,
      "Saudi Arabia": 5.75,
      "Scotland": 12.1,
      "Iraq": 1.6,
      "New Zealand": 2.8000000000000003,
      "Panama": 1.5,
      "Turkey": 3.5999999999999996,
      "Uzbekistan": 1.4500000000000002,
      "Haiti": 0.1,
      "Curacao": 0.65,
      "Tunisia": 0.7000000000000001
    },
    "r16": {
      "Korea Republic": 55.7,
      "Qatar": 12.15,
      "Germany": 75.94999999999999,
      "South Africa": 11.600000000000001,
      "Sweden": 34.949999999999996,
      "Morocco": 46.800000000000004,
      "Brazil": 64.95,
      "Japan": 36.4,
      "Norway": 30.0,
      "Australia": 52.6,
      "Ecuador": 17.549999999999997,
      "France": 78.5,
      "Mexico": 61.25000000000001,
      "Cote d'Ivoire": 43.35,
      "England": 76.05,
      "Senegal": 35.5,
      "USA": 65.14999999999999,
      "Netherlands": 48.8,
      "IR Iran": 23.3,
      "Jordan": 7.55,
      "Colombia": 58.35,
      "Croatia": 41.4,
      "Spain": 56.75,
      "Argentina": 67.95,
      "Switzerland": 46.1,
      "Belgium": 63.4,
      "Austria": 37.65,
      "Uruguay": 36.15,
      "Portugal": 70.85000000000001,
      "Ghana": 14.85,
      "Paraguay": 8.95,
      "Egypt": 30.75,
      "Czechia": 11.75,
      "Bosnia and Herzegovina": 20.3,
      "Cabo Verde": 9.1,
      "DR Congo": 10.65,
      "Algeria": 17.0,
      "Canada": 30.15,
      "Saudi Arabia": 15.299999999999999,
      "Scotland": 26.950000000000003,
      "Iraq": 8.5,
      "New Zealand": 10.5,
      "Panama": 4.8500000000000005,
      "Turkey": 10.75,
      "Uzbekistan": 5.1499999999999995,
      "Haiti": 1.2,
      "Curacao": 4.45,
      "Tunisia": 2.15
    },
    "r32": {
      "Korea Republic": 94.39999999999999,
      "Qatar": 44.35,
      "Germany": 99.8,
      "South Africa": 33.0,
      "Sweden": 97.7,
      "Morocco": 91.85,
      "Brazil": 97.55,
      "Japan": 86.6,
      "Norway": 65.35,
      "Australia": 96.3,
      "Ecuador": 49.65,
      "France": 97.8,
      "Mexico": 97.95,
      "Cote d'Ivoire": 92.65,
      "England": 97.8,
      "Senegal": 72.8,
      "USA": 99.35000000000001,
      "Netherlands": 92.5,
      "IR Iran": 54.400000000000006,
      "Jordan": 30.9,
      "Colombia": 94.19999999999999,
      "Croatia": 85.65,
      "Spain": 92.10000000000001,
      "Argentina": 97.65,
      "Switzerland": 84.3,
      "Belgium": 93.25,
      "Austria": 81.55,
      "Uruguay": 81.3,
      "Portugal": 97.15,
      "Ghana": 55.05,
      "Paraguay": 29.599999999999998,
      "Egypt": 74.85000000000001,
      "Czechia": 41.199999999999996,
      "Bosnia and Herzegovina": 64.45,
      "Cabo Verde": 42.9,
      "DR Congo": 43.6,
      "Algeria": 54.900000000000006,
      "Canada": 75.1,
      "Saudi Arabia": 53.800000000000004,
      "Scotland": 77.85,
      "Iraq": 29.049999999999997,
      "New Zealand": 34.150000000000006,
      "Panama": 27.150000000000002,
      "Turkey": 35.85,
      "Uzbekistan": 26.5,
      "Haiti": 9.5,
      "Curacao": 16.650000000000002,
      "Tunisia": 8.0
    },
    "_match_count": 16
  },
  "2026-06-16": {
    "win": {
      "Korea Republic": 0.0,
      "Bosnia and Herzegovina": 0.0,
      "Germany": 0.0,
      "Czechia": 0.0,
      "Netherlands": 0.0,
      "Scotland": 0.0,
      "Brazil": 0.0,
      "Japan": 0.0,
      "France": 0.0,
      "Australia": 0.0,
      "Cote d'Ivoire": 0.0,
      "Norway": 0.0,
      "Mexico": 0.0,
      "Morocco": 0.0,
      "England": 0.0,
      "Cabo Verde": 0.0,
      "USA": 0.0,
      "Qatar": 0.0,
      "Belgium": 0.0,
      "Jordan": 0.0,
      "Colombia": 0.0,
      "Croatia": 0.0,
      "Uruguay": 0.0,
      "Argentina": 0.0,
      "Switzerland": 0.0,
      "Tunisia": 0.0,
      "Austria": 0.0,
      "Spain": 0.0,
      "Portugal": 0.0,
      "Ghana": 0.0,
      "Turkey": 0.0,
      "New Zealand": 0.0,
      "South Africa": 0.0,
      "Sweden": 0.0,
      "Curacao": 0.0,
      "Canada": 0.0,
      "Saudi Arabia": 0.0,
      "Senegal": 0.0,
      "Paraguay": 0.0,
      "Egypt": 0.0,
      "Panama": 0.0,
      "Haiti": 0.0,
      "Ecuador": 0.0,
      "Algeria": 0.0,
      "IR Iran": 0.0,
      "DR Congo": 0.0,
      "Uzbekistan": 0.0,
      "Iraq": 0.0
    },
    "final": {
      "Korea Republic": 2.9000000000000004,
      "Bosnia and Herzegovina": 0.44999999999999996,
      "Germany": 12.65,
      "Czechia": 0.35000000000000003,
      "Netherlands": 8.05,
      "Scotland": 2.0500000000000003,
      "Brazil": 16.650000000000002,
      "Japan": 3.5000000000000004,
      "France": 23.7,
      "Australia": 2.5,
      "Cote d'Ivoire": 2.15,
      "Norway": 3.25,
      "Mexico": 5.050000000000001,
      "Morocco": 6.35,
      "England": 18.7,
      "Cabo Verde": 0.25,
      "USA": 7.9,
      "Qatar": 0.15,
      "Belgium": 6.15,
      "Jordan": 0.15,
      "Colombia": 7.35,
      "Croatia": 2.85,
      "Uruguay": 3.55,
      "Argentina": 20.5,
      "Switzerland": 2.8000000000000003,
      "Tunisia": 0.1,
      "Austria": 3.0,
      "Spain": 11.35,
      "Portugal": 15.9,
      "Ghana": 0.5499999999999999,
      "Turkey": 0.5499999999999999,
      "New Zealand": 0.1,
      "South Africa": 0.2,
      "Sweden": 2.75,
      "Curacao": 0.1,
      "Canada": 0.8500000000000001,
      "Saudi Arabia": 0.35000000000000003,
      "Senegal": 1.5,
      "Paraguay": 0.25,
      "Egypt": 0.75,
      "Panama": 0.0,
      "Haiti": 0.0,
      "Ecuador": 0.35000000000000003,
      "Algeria": 0.4,
      "IR Iran": 0.35000000000000003,
      "DR Congo": 0.4,
      "Uzbekistan": 0.15,
      "Iraq": 0.1
    },
    "sf": {
      "Korea Republic": 7.5,
      "Bosnia and Herzegovina": 1.5,
      "Germany": 21.65,
      "Czechia": 0.95,
      "Netherlands": 15.7,
      "Scotland": 4.5,
      "Brazil": 28.249999999999996,
      "Japan": 7.35,
      "France": 36.25,
      "Australia": 8.0,
      "Cote d'Ivoire": 5.25,
      "Norway": 7.1499999999999995,
      "Mexico": 10.9,
      "Morocco": 12.45,
      "England": 31.45,
      "Cabo Verde": 1.15,
      "USA": 17.549999999999997,
      "Qatar": 0.5,
      "Belgium": 15.6,
      "Jordan": 0.35000000000000003,
      "Colombia": 16.2,
      "Croatia": 8.05,
      "Uruguay": 9.25,
      "Argentina": 36.0,
      "Switzerland": 7.1499999999999995,
      "Tunisia": 0.3,
      "Austria": 7.6,
      "Spain": 22.45,
      "Portugal": 28.9,
      "Ghana": 1.9,
      "Turkey": 1.6,
      "New Zealand": 0.7000000000000001,
      "South Africa": 0.75,
      "Sweden": 6.1,
      "Curacao": 0.5,
      "Canada": 3.0,
      "Saudi Arabia": 1.4000000000000001,
      "Senegal": 4.1000000000000005,
      "Paraguay": 1.2,
      "Egypt": 2.55,
      "Panama": 0.4,
      "Haiti": 0.0,
      "Ecuador": 1.55,
      "Algeria": 1.15,
      "IR Iran": 1.7000000000000002,
      "DR Congo": 1.0,
      "Uzbekistan": 0.3,
      "Iraq": 0.2
    },
    "qf": {
      "Korea Republic": 19.900000000000002,
      "Bosnia and Herzegovina": 5.800000000000001,
      "Germany": 38.15,
      "Czechia": 3.4000000000000004,
      "Netherlands": 32.300000000000004,
      "Scotland": 12.65,
      "Brazil": 47.199999999999996,
      "Japan": 18.95,
      "France": 52.1,
      "Australia": 20.3,
      "Cote d'Ivoire": 13.25,
      "Norway": 16.400000000000002,
      "Mexico": 27.250000000000004,
      "Morocco": 28.4,
      "England": 49.5,
      "Cabo Verde": 3.25,
      "USA": 35.949999999999996,
      "Qatar": 2.25,
      "Belgium": 33.2,
      "Jordan": 2.25,
      "Colombia": 33.15,
      "Croatia": 19.75,
      "Uruguay": 20.0,
      "Argentina": 54.50000000000001,
      "Switzerland": 18.75,
      "Tunisia": 0.95,
      "Austria": 17.150000000000002,
      "Spain": 35.9,
      "Portugal": 49.25,
      "Ghana": 5.35,
      "Turkey": 3.85,
      "New Zealand": 2.15,
      "South Africa": 2.85,
      "Sweden": 15.5,
      "Curacao": 1.15,
      "Canada": 10.549999999999999,
      "Saudi Arabia": 4.05,
      "Senegal": 10.65,
      "Paraguay": 2.5,
      "Egypt": 8.7,
      "Panama": 1.4500000000000002,
      "Haiti": 0.4,
      "Ecuador": 4.6,
      "Algeria": 3.55,
      "IR Iran": 6.25,
      "DR Congo": 2.9499999999999997,
      "Uzbekistan": 1.0,
      "Iraq": 0.65
    },
    "r16": {
      "Korea Republic": 54.35,
      "Bosnia and Herzegovina": 19.75,
      "Germany": 75.7,
      "Czechia": 12.85,
      "Netherlands": 48.9,
      "Scotland": 26.35,
      "Brazil": 65.14999999999999,
      "Japan": 36.35,
      "France": 79.25,
      "Australia": 53.15,
      "Cote d'Ivoire": 42.85,
      "Norway": 45.65,
      "Mexico": 61.8,
      "Morocco": 47.099999999999994,
      "England": 73.4,
      "Cabo Verde": 9.25,
      "USA": 67.2,
      "Qatar": 11.05,
      "Belgium": 64.60000000000001,
      "Jordan": 8.3,
      "Colombia": 56.10000000000001,
      "Croatia": 42.4,
      "Uruguay": 37.0,
      "Argentina": 72.89999999999999,
      "Switzerland": 48.449999999999996,
      "Tunisia": 2.85,
      "Austria": 35.8,
      "Spain": 56.15,
      "Portugal": 70.45,
      "Ghana": 15.0,
      "Turkey": 11.1,
      "New Zealand": 10.0,
      "South Africa": 10.65,
      "Sweden": 33.95,
      "Curacao": 4.75,
      "Canada": 32.05,
      "Saudi Arabia": 13.850000000000001,
      "Senegal": 29.15,
      "Paraguay": 9.3,
      "Egypt": 30.0,
      "Panama": 5.3,
      "Haiti": 1.55,
      "Ecuador": 17.05,
      "Algeria": 10.549999999999999,
      "IR Iran": 22.0,
      "DR Congo": 10.45,
      "Uzbekistan": 5.7,
      "Iraq": 2.5
    },
    "r32": {
      "Korea Republic": 95.05,
      "Bosnia and Herzegovina": 63.7,
      "Germany": 99.85000000000001,
      "Czechia": 42.5,
      "Netherlands": 93.89999999999999,
      "Scotland": 77.05,
      "Brazil": 97.2,
      "Japan": 87.6,
      "France": 99.75,
      "Australia": 96.3,
      "Cote d'Ivoire": 92.2,
      "Norway": 96.45,
      "Mexico": 98.0,
      "Morocco": 93.35,
      "England": 97.89999999999999,
      "Cabo Verde": 40.849999999999994,
      "USA": 99.4,
      "Qatar": 45.45,
      "Belgium": 94.5,
      "Jordan": 31.900000000000002,
      "Colombia": 93.30000000000001,
      "Croatia": 85.6,
      "Uruguay": 81.6,
      "Argentina": 99.7,
      "Switzerland": 86.8,
      "Tunisia": 8.95,
      "Austria": 84.15,
      "Spain": 91.60000000000001,
      "Portugal": 97.5,
      "Ghana": 52.900000000000006,
      "Turkey": 37.6,
      "New Zealand": 35.199999999999996,
      "South Africa": 31.45,
      "Sweden": 96.55,
      "Curacao": 18.05,
      "Canada": 75.5,
      "Saudi Arabia": 55.300000000000004,
      "Senegal": 65.85,
      "Paraguay": 29.549999999999997,
      "Egypt": 75.14999999999999,
      "Panama": 26.950000000000003,
      "Haiti": 8.9,
      "Ecuador": 49.15,
      "Algeria": 37.65,
      "IR Iran": 53.55,
      "DR Congo": 43.3,
      "Uzbekistan": 26.05,
      "Iraq": 9.25
    },
    "_match_count": 19
  },
  "2026-06-17": {
    "win": {
      "Mexico": 0.0,
      "Canada": 0.0,
      "Germany": 0.0,
      "Korea Republic": 0.0,
      "Netherlands": 0.0,
      "Morocco": 0.0,
      "Brazil": 0.0,
      "Japan": 0.0,
      "France": 0.0,
      "Scotland": 0.0,
      "Ecuador": 0.0,
      "Senegal": 0.0,
      "Czechia": 0.0,
      "Cote d'Ivoire": 0.0,
      "England": 0.0,
      "Portugal": 0.0,
      "Australia": 0.0,
      "Sweden": 0.0,
      "Belgium": 0.0,
      "Uruguay": 0.0,
      "Uzbekistan": 0.0,
      "Croatia": 0.0,
      "Spain": 0.0,
      "Austria": 0.0,
      "Switzerland": 0.0,
      "Norway": 0.0,
      "Argentina": 0.0,
      "Cabo Verde": 0.0,
      "Colombia": 0.0,
      "Algeria": 0.0,
      "USA": 0.0,
      "IR Iran": 0.0,
      "Qatar": 0.0,
      "New Zealand": 0.0,
      "Panama": 0.0,
      "Saudi Arabia": 0.0,
      "Turkey": 0.0,
      "South Africa": 0.0,
      "DR Congo": 0.0,
      "Jordan": 0.0,
      "Egypt": 0.0,
      "Ghana": 0.0,
      "Bosnia and Herzegovina": 0.0,
      "Paraguay": 0.0,
      "Curacao": 0.0,
      "Haiti": 0.0,
      "Iraq": 0.0,
      "Tunisia": 0.0
    },
    "final": {
      "Mexico": 4.55,
      "Canada": 1.0,
      "Germany": 12.1,
      "Korea Republic": 3.6999999999999997,
      "Netherlands": 8.4,
      "Morocco": 6.6000000000000005,
      "Brazil": 17.0,
      "Japan": 2.8000000000000003,
      "France": 24.45,
      "Scotland": 1.7500000000000002,
      "Ecuador": 0.8,
      "Senegal": 1.4500000000000002,
      "Czechia": 0.2,
      "Cote d'Ivoire": 2.35,
      "England": 22.8,
      "Portugal": 12.25,
      "Australia": 2.9499999999999997,
      "Sweden": 3.0,
      "Belgium": 7.1499999999999995,
      "Uruguay": 3.25,
      "Uzbekistan": 0.05,
      "Croatia": 2.0500000000000003,
      "Spain": 10.65,
      "Austria": 3.9,
      "Switzerland": 2.4,
      "Norway": 3.0,
      "Argentina": 18.5,
      "Cabo Verde": 0.44999999999999996,
      "Colombia": 8.75,
      "Algeria": 0.4,
      "USA": 7.049999999999999,
      "IR Iran": 0.4,
      "Qatar": 0.1,
      "New Zealand": 0.1,
      "Panama": 0.05,
      "Saudi Arabia": 0.6,
      "Turkey": 0.44999999999999996,
      "South Africa": 0.05,
      "DR Congo": 0.4,
      "Jordan": 0.15,
      "Egypt": 0.75,
      "Ghana": 0.44999999999999996,
      "Bosnia and Herzegovina": 0.25,
      "Paraguay": 0.4,
      "Curacao": 0.05,
      "Haiti": 0.0,
      "Iraq": 0.0,
      "Tunisia": 0.05
    },
    "sf": {
      "Mexico": 10.15,
      "Canada": 3.25,
      "Germany": 21.4,
      "Korea Republic": 7.35,
      "Netherlands": 14.799999999999999,
      "Morocco": 11.85,
      "Brazil": 26.150000000000002,
      "Japan": 7.449999999999999,
      "France": 35.8,
      "Scotland": 3.95,
      "Ecuador": 1.7000000000000002,
      "Senegal": 4.05,
      "Czechia": 0.75,
      "Cote d'Ivoire": 5.6000000000000005,
      "England": 36.35,
      "Portugal": 24.45,
      "Australia": 9.3,
      "Sweden": 6.05,
      "Belgium": 17.25,
      "Uruguay": 8.95,
      "Uzbekistan": 0.05,
      "Croatia": 6.5,
      "Spain": 21.55,
      "Austria": 11.200000000000001,
      "Switzerland": 7.1499999999999995,
      "Norway": 6.6000000000000005,
      "Argentina": 34.699999999999996,
      "Cabo Verde": 1.35,
      "Colombia": 19.0,
      "Algeria": 1.6500000000000001,
      "USA": 16.35,
      "IR Iran": 2.45,
      "Qatar": 0.65,
      "New Zealand": 0.5499999999999999,
      "Panama": 0.3,
      "Saudi Arabia": 1.6500000000000001,
      "Turkey": 1.0999999999999999,
      "South Africa": 0.65,
      "DR Congo": 1.7500000000000002,
      "Jordan": 0.3,
      "Egypt": 3.3000000000000003,
      "Ghana": 1.8499999999999999,
      "Bosnia and Herzegovina": 1.25,
      "Paraguay": 1.0999999999999999,
      "Curacao": 0.2,
      "Haiti": 0.0,
      "Iraq": 0.15,
      "Tunisia": 0.05
    },
    "qf": {
      "Mexico": 24.6,
      "Canada": 10.25,
      "Germany": 38.2,
      "Korea Republic": 18.75,
      "Netherlands": 30.349999999999998,
      "Morocco": 27.650000000000002,
      "Brazil": 44.75,
      "Japan": 19.400000000000002,
      "France": 53.6,
      "Scotland": 11.700000000000001,
      "Ecuador": 4.3999999999999995,
      "Senegal": 10.35,
      "Czechia": 3.15,
      "Cote d'Ivoire": 13.950000000000001,
      "England": 58.050000000000004,
      "Portugal": 42.05,
      "Australia": 22.6,
      "Sweden": 16.35,
      "Belgium": 33.4,
      "Uruguay": 18.65,
      "Uzbekistan": 1.0999999999999999,
      "Croatia": 15.049999999999999,
      "Spain": 34.599999999999994,
      "Austria": 22.25,
      "Switzerland": 19.85,
      "Norway": 17.299999999999997,
      "Argentina": 53.949999999999996,
      "Cabo Verde": 3.75,
      "Colombia": 36.5,
      "Algeria": 4.25,
      "USA": 33.650000000000006,
      "IR Iran": 7.35,
      "Qatar": 2.55,
      "New Zealand": 1.8499999999999999,
      "Panama": 1.5,
      "Saudi Arabia": 4.7,
      "Turkey": 3.5999999999999996,
      "South Africa": 2.8000000000000003,
      "DR Congo": 5.2,
      "Jordan": 1.25,
      "Egypt": 8.85,
      "Ghana": 5.45,
      "Bosnia and Herzegovina": 5.4,
      "Paraguay": 2.65,
      "Curacao": 1.05,
      "Haiti": 0.25,
      "Iraq": 0.65,
      "Tunisia": 0.44999999999999996
    },
    "r16": {
      "Mexico": 63.24999999999999,
      "Canada": 32.4,
      "Germany": 76.5,
      "Korea Republic": 54.35,
      "Netherlands": 48.15,
      "Morocco": 45.5,
      "Brazil": 64.1,
      "Japan": 37.45,
      "France": 79.05,
      "Scotland": 26.400000000000002,
      "Ecuador": 16.8,
      "Senegal": 27.85,
      "Czechia": 12.65,
      "Cote d'Ivoire": 43.1,
      "England": 78.85,
      "Portugal": 64.95,
      "Australia": 53.75,
      "Sweden": 36.0,
      "Belgium": 63.74999999999999,
      "Uruguay": 35.9,
      "Uzbekistan": 3.85,
      "Croatia": 35.199999999999996,
      "Spain": 53.449999999999996,
      "Austria": 41.4,
      "Switzerland": 46.949999999999996,
      "Norway": 47.449999999999996,
      "Argentina": 72.3,
      "Cabo Verde": 9.950000000000001,
      "Colombia": 60.650000000000006,
      "Algeria": 11.35,
      "USA": 65.60000000000001,
      "IR Iran": 22.25,
      "Qatar": 10.75,
      "New Zealand": 10.5,
      "Panama": 5.7,
      "Saudi Arabia": 13.65,
      "Turkey": 11.799999999999999,
      "South Africa": 10.6,
      "DR Congo": 16.2,
      "Jordan": 4.35,
      "Egypt": 30.9,
      "Ghana": 16.6,
      "Bosnia and Herzegovina": 19.7,
      "Paraguay": 8.3,
      "Curacao": 4.75,
      "Haiti": 1.0999999999999999,
      "Iraq": 2.15,
      "Tunisia": 1.7999999999999998
    },
    "r32": {
      "Mexico": 98.3,
      "Canada": 78.35,
      "Germany": 99.75,
      "Korea Republic": 95.0,
      "Netherlands": 91.55,
      "Morocco": 91.8,
      "Brazil": 96.85000000000001,
      "Japan": 87.15,
      "France": 99.75,
      "Scotland": 78.5,
      "Ecuador": 49.15,
      "Senegal": 65.35,
      "Czechia": 42.449999999999996,
      "Cote d'Ivoire": 91.75,
      "England": 99.85000000000001,
      "Portugal": 94.5,
      "Australia": 96.7,
      "Sweden": 96.7,
      "Belgium": 94.45,
      "Uruguay": 81.55,
      "Uzbekistan": 23.75,
      "Croatia": 79.05,
      "Spain": 90.95,
      "Austria": 96.15,
      "Switzerland": 84.75,
      "Norway": 96.45,
      "Argentina": 99.9,
      "Cabo Verde": 42.6,
      "Colombia": 92.55,
      "Algeria": 38.0,
      "USA": 99.1,
      "IR Iran": 51.949999999999996,
      "Qatar": 43.65,
      "New Zealand": 35.8,
      "Panama": 27.800000000000004,
      "Saudi Arabia": 54.2,
      "Turkey": 36.25,
      "South Africa": 32.550000000000004,
      "DR Congo": 60.45,
      "Jordan": 18.0,
      "Egypt": 75.6,
      "Ghana": 54.1,
      "Bosnia and Herzegovina": 64.5,
      "Paraguay": 29.5,
      "Curacao": 17.4,
      "Haiti": 8.3,
      "Iraq": 8.95,
      "Tunisia": 8.3
    },
    "_match_count": 22
  },
  "2026-06-18": {
    "win": {
      "Korea Republic": 0.0,
      "Switzerland": 0.0,
      "Cote d'Ivoire": 0.0,
      "Qatar": 0.0,
      "Japan": 0.0,
      "Morocco": 0.0,
      "Brazil": 0.0,
      "Sweden": 0.0,
      "Norway": 0.0,
      "Scotland": 0.0,
      "Germany": 0.0,
      "France": 0.0,
      "Mexico": 0.0,
      "Spain": 0.0,
      "England": 0.0,
      "DR Congo": 0.0,
      "USA": 0.0,
      "Senegal": 0.0,
      "IR Iran": 0.0,
      "Algeria": 0.0,
      "Colombia": 0.0,
      "Ghana": 0.0,
      "Uruguay": 0.0,
      "Argentina": 0.0,
      "Canada": 0.0,
      "Belgium": 0.0,
      "Austria": 0.0,
      "Saudi Arabia": 0.0,
      "Portugal": 0.0,
      "Croatia": 0.0,
      "Australia": 0.0,
      "Egypt": 0.0,
      "Netherlands": 0.0,
      "Paraguay": 0.0,
      "New Zealand": 0.0,
      "Cabo Verde": 0.0,
      "Panama": 0.0,
      "Ecuador": 0.0,
      "South Africa": 0.0,
      "Jordan": 0.0,
      "Turkey": 0.0,
      "Czechia": 0.0,
      "Curacao": 0.0,
      "Bosnia and Herzegovina": 0.0,
      "Tunisia": 0.0,
      "Iraq": 0.0,
      "Uzbekistan": 0.0,
      "Haiti": 0.0
    },
    "final": {
      "Korea Republic": 3.55,
      "Switzerland": 3.35,
      "Cote d'Ivoire": 2.45,
      "Qatar": 0.2,
      "Japan": 3.0,
      "Morocco": 6.05,
      "Brazil": 17.150000000000002,
      "Sweden": 2.55,
      "Norway": 2.65,
      "Scotland": 1.9,
      "Germany": 13.350000000000001,
      "France": 23.549999999999997,
      "Mexico": 5.1,
      "Spain": 11.05,
      "England": 21.8,
      "DR Congo": 0.6,
      "USA": 7.8,
      "Senegal": 1.4000000000000001,
      "IR Iran": 0.5499999999999999,
      "Algeria": 0.25,
      "Colombia": 6.8500000000000005,
      "Ghana": 0.4,
      "Uruguay": 4.3999999999999995,
      "Argentina": 19.5,
      "Canada": 1.15,
      "Belgium": 8.25,
      "Austria": 3.8,
      "Saudi Arabia": 0.44999999999999996,
      "Portugal": 11.75,
      "Croatia": 2.0,
      "Australia": 2.9499999999999997,
      "Egypt": 0.6,
      "Netherlands": 7.9,
      "Paraguay": 0.2,
      "New Zealand": 0.1,
      "Cabo Verde": 0.1,
      "Panama": 0.05,
      "Ecuador": 0.3,
      "South Africa": 0.25,
      "Jordan": 0.0,
      "Turkey": 0.2,
      "Czechia": 0.15,
      "Curacao": 0.15,
      "Bosnia and Herzegovina": 0.1,
      "Tunisia": 0.05,
      "Iraq": 0.05,
      "Uzbekistan": 0.0,
      "Haiti": 0.0
    },
    "sf": {
      "Korea Republic": 6.550000000000001,
      "Switzerland": 9.5,
      "Cote d'Ivoire": 5.45,
      "Qatar": 0.35000000000000003,
      "Japan": 6.75,
      "Morocco": 12.15,
      "Brazil": 26.85,
      "Sweden": 5.8500000000000005,
      "Norway": 6.550000000000001,
      "Scotland": 4.5,
      "Germany": 21.9,
      "France": 36.9,
      "Mexico": 10.15,
      "Spain": 22.25,
      "England": 35.199999999999996,
      "DR Congo": 2.0500000000000003,
      "USA": 18.05,
      "Senegal": 3.5999999999999996,
      "IR Iran": 2.3,
      "Algeria": 1.05,
      "Colombia": 16.0,
      "Ghana": 1.5,
      "Uruguay": 9.75,
      "Argentina": 36.6,
      "Canada": 2.65,
      "Belgium": 18.8,
      "Austria": 9.9,
      "Saudi Arabia": 1.7500000000000002,
      "Portugal": 24.25,
      "Croatia": 5.7,
      "Australia": 9.8,
      "Egypt": 2.7,
      "Netherlands": 14.799999999999999,
      "Paraguay": 0.95,
      "New Zealand": 0.5,
      "Cabo Verde": 0.7000000000000001,
      "Panama": 0.5,
      "Ecuador": 1.5,
      "South Africa": 0.5499999999999999,
      "Jordan": 0.15,
      "Turkey": 1.15,
      "Czechia": 0.8500000000000001,
      "Curacao": 0.3,
      "Bosnia and Herzegovina": 0.3,
      "Tunisia": 0.15,
      "Iraq": 0.1,
      "Uzbekistan": 0.1,
      "Haiti": 0.05
    },
    "qf": {
      "Korea Republic": 19.55,
      "Switzerland": 26.35,
      "Cote d'Ivoire": 14.899999999999999,
      "Qatar": 2.85,
      "Japan": 17.9,
      "Morocco": 28.95,
      "Brazil": 46.0,
      "Sweden": 15.4,
      "Norway": 17.25,
      "Scotland": 11.799999999999999,
      "Germany": 35.099999999999994,
      "France": 54.05,
      "Mexico": 23.9,
      "Spain": 35.9,
      "England": 57.3,
      "DR Congo": 5.050000000000001,
      "USA": 35.25,
      "Senegal": 10.5,
      "IR Iran": 7.6499999999999995,
      "Algeria": 4.45,
      "Colombia": 34.599999999999994,
      "Ghana": 5.6000000000000005,
      "Uruguay": 19.3,
      "Argentina": 52.05,
      "Canada": 10.45,
      "Belgium": 33.75,
      "Austria": 21.15,
      "Saudi Arabia": 5.0,
      "Portugal": 43.7,
      "Croatia": 14.6,
      "Australia": 21.45,
      "Egypt": 8.55,
      "Netherlands": 30.7,
      "Paraguay": 2.6,
      "New Zealand": 2.15,
      "Cabo Verde": 3.0,
      "Panama": 1.9,
      "Ecuador": 4.35,
      "South Africa": 2.0500000000000003,
      "Jordan": 1.2,
      "Turkey": 3.4000000000000004,
      "Czechia": 2.55,
      "Curacao": 1.05,
      "Bosnia and Herzegovina": 2.1999999999999997,
      "Tunisia": 0.7000000000000001,
      "Iraq": 0.65,
      "Uzbekistan": 0.8,
      "Haiti": 0.4
    },
    "r16": {
      "Korea Republic": 56.05,
      "Switzerland": 60.650000000000006,
      "Cote d'Ivoire": 42.55,
      "Qatar": 12.25,
      "Japan": 35.15,
      "Morocco": 48.15,
      "Brazil": 64.14999999999999,
      "Sweden": 34.2,
      "Norway": 47.05,
      "Scotland": 27.200000000000003,
      "Germany": 76.1,
      "France": 79.45,
      "Mexico": 61.8,
      "Spain": 55.300000000000004,
      "England": 78.85,
      "DR Congo": 16.1,
      "USA": 66.05,
      "Senegal": 28.15,
      "IR Iran": 21.85,
      "Algeria": 11.3,
      "Colombia": 59.699999999999996,
      "Ghana": 17.0,
      "Uruguay": 36.9,
      "Argentina": 71.85000000000001,
      "Canada": 30.099999999999998,
      "Belgium": 62.2,
      "Austria": 41.699999999999996,
      "Saudi Arabia": 13.900000000000002,
      "Portugal": 67.10000000000001,
      "Croatia": 34.050000000000004,
      "Australia": 52.05,
      "Egypt": 29.799999999999997,
      "Netherlands": 48.449999999999996,
      "Paraguay": 9.4,
      "New Zealand": 10.5,
      "Cabo Verde": 10.2,
      "Panama": 6.65,
      "Ecuador": 17.549999999999997,
      "South Africa": 8.25,
      "Jordan": 4.3,
      "Turkey": 11.75,
      "Czechia": 8.3,
      "Curacao": 5.3,
      "Bosnia and Herzegovina": 10.0,
      "Tunisia": 1.8499999999999999,
      "Iraq": 2.75,
      "Uzbekistan": 4.55,
      "Haiti": 1.5
    },
    "r32": {
      "Korea Republic": 94.3,
      "Switzerland": 100.0,
      "Cote d'Ivoire": 92.2,
      "Qatar": 49.5,
      "Japan": 86.15,
      "Morocco": 92.30000000000001,
      "Brazil": 97.6,
      "Sweden": 97.25,
      "Norway": 97.3,
      "Scotland": 78.8,
      "Germany": 99.9,
      "France": 99.55000000000001,
      "Mexico": 96.65,
      "Spain": 91.45,
      "England": 99.45,
      "DR Congo": 62.6,
      "USA": 99.4,
      "Senegal": 66.45,
      "IR Iran": 53.849999999999994,
      "Algeria": 38.4,
      "Colombia": 93.7,
      "Ghana": 55.7,
      "Uruguay": 83.55,
      "Argentina": 99.7,
      "Canada": 75.55,
      "Belgium": 93.8,
      "Austria": 97.0,
      "Saudi Arabia": 54.6,
      "Portugal": 94.69999999999999,
      "Croatia": 78.3,
      "Australia": 96.35000000000001,
      "Egypt": 75.0,
      "Netherlands": 93.7,
      "Paraguay": 31.55,
      "New Zealand": 35.8,
      "Cabo Verde": 42.4,
      "Panama": 30.3,
      "Ecuador": 49.75,
      "South Africa": 23.200000000000003,
      "Jordan": 20.8,
      "Turkey": 38.4,
      "Czechia": 21.9,
      "Curacao": 20.150000000000002,
      "Bosnia and Herzegovina": 45.0,
      "Tunisia": 10.2,
      "Iraq": 11.3,
      "Uzbekistan": 23.95,
      "Haiti": 10.549999999999999
    },
    "_match_count": 24
  }
}